{
  "symbol": "EUR/USD",
  "name": "Euro vs US Dollar",
  "nameCn": "欧元/美元",
  "timestamp": "2025-11-12T13:47:42.202Z",
  "price": {
    "close": "1.15698",
    "high": "1.15790",
    "low": "1.15674",
    "open": "1.15769",
    "change": "-0.05",
    "datetime": "2025-11-13 00:00:00"
  },
  "indicators": {
    "rsi": 44.4765,
    "macd": -0.000031335333,
    "macd_signal": 0.00013342065,
    "sma20": 1.15793
  },
  "analysis": {
    "zh": {
      "title": "欧元/美元技术分析：[震荡整理中]",
      "content": "当前欧元/美元的价格为1.15698，整体呈现出震荡整理的趋势。在过去24小时内，价格变化微小，只有-0.05%。高点1.15790和低点1.15674的波动范围显示出市场缺乏明显的方向性，投资者可能在等待更明确的市场信号。\n\n从技术指标来看，虽然RSI和MACD的具体数值尚不可用，但结合当前价格走势，SMA(20)的值为1.15793，表明短期内价格仍在其移动平均线附近徘徊。这可能意味着市场正在进行短期调整，投资者情绪较为谨慎。\n\n在支撑和阻力位方面，当前支撑位可看作1.15674，若价格跌破该水平，可能进一步下探。阻力位则在1.15790附近，若突破该点，可能会引发短期的买入信号。因此，投资者需密切关注这两个关键水平的变化。\n\n基于以上分析，建议交易者在当前震荡区间内采取观望策略，关注价格突破支撑或阻力位后的进一步走势。若价格突破1.15790，可以考虑短期买入；反之，则需谨慎面对可能的下行风险。"
    },
    "en": {
      "title": "Euro vs US Dollar Technical Analysis",
      "content": "The EUR/USD currency pair is currently trading at 1.15698, reflecting a slight decline of 0.05% over the last 24 hours. The price action has remained relatively stable within a tight range, with a 24-hour high of 1.15790 and a low of 1.15674. This consolidation phase suggests indecision in the market, as traders weigh various economic factors affecting both the Eurozone and the U.S. economy. A breakout from this range could provide insights into the next directional move.\n\nFrom a technical perspective, the Simple Moving Average (SMA) at 20 periods is positioned at 1.15793, indicating that the price is currently below this average. This situation may suggest a bearish short-term trend, yet the proximity to the SMA indicates that the market could reverse if it finds enough bullish momentum. The MACD value of -0.000031335333 reinforces this bearish sentiment, although the lack of an accompanying signal makes it crucial for traders to monitor upcoming price action for confirmation.\n\nKey support and resistance levels are critical in determining potential entry and exit points. The immediate support level can be identified at 1.15674, which, if broken, could lead to further declines toward the next support around 1.15500. Conversely, resistance is likely to be found at 1.15790; a breakout above this level may signal a bullish reversal and open the door for an upward movement toward the 1.16000 area.\n\nTraders should consider employing a cautious approach in the current market conditions. A wait-and-see strategy may be beneficial, allowing for a clearer signal to emerge. For aggressive traders, short positions could be considered near the resistance level, while long positions may be warranted if the price breaks convincingly above the SMA and resistance zone. Keeping an eye on key economic indicators and geopolitical developments will be essential for making informed trading decisions."
    }
  }
}